digitaltwin_dataspace/__init__.py
digitaltwin_dataspace/cli.py
digitaltwin_dataspace/components/__init__.py
digitaltwin_dataspace/components/collector.py
digitaltwin_dataspace/components/handler.py
digitaltwin_dataspace/components/harvester.py
digitaltwin_dataspace/configuration/__init__.py
digitaltwin_dataspace/configuration/load.py
digitaltwin_dataspace/configuration/model.py
digitaltwin_dataspace/data/__init__.py
digitaltwin_dataspace/data/engine.py
digitaltwin_dataspace/data/retrieve.py
digitaltwin_dataspace/data/storage.py
digitaltwin_dataspace/data/sync_db.py
digitaltwin_dataspace/data/table.py
digitaltwin_dataspace/data/write.py
digitaltwin_dataspace/runners/__init__.py
digitaltwin_dataspace/runners/_utils.py
digitaltwin_dataspace/runners/run_collector.py
digitaltwin_dataspace/runners/run_handler.py
digitaltwin_dataspace/runners/run_harvester.py
digitaltwin_dataspace-0.0.1.dist-info/METADATA
digitaltwin_dataspace-0.0.1.dist-info/WHEEL
digitaltwin_dataspace-0.0.1.dist-info/entry_points.txt
digitaltwin_dataspace-0.0.1.dist-info/top_level.txt
digitaltwin_dataspace-0.0.1.dist-info/RECORD
