Metadata-Version: 2.4
Name: digitaltwin_dataspace
Version: 0.0.1
Summary: DigitalTwin - Dataspace is a Python package that provides a simple and efficient way to create, manage, and query data spaces.
Author-email: Gaspard Merten <gaspard@norse.be>
License-Expression: CC-BY-NC-SA-4.0
Project-URL: Homepage, https://github.com/GaspardMerten/digitaltwin
Project-URL: Bug Tracker, https://github.com/GaspardMerten/digitaltwin/issues
Classifier: Programming Language :: Python :: 3
Classifier: Operating System :: OS Independent
Requires-Python: >=3.8
Requires-Dist: requests
Requires-Dist: SQLAlchemy
Requires-Dist: azure-storage-blob
Requires-Dist: schedule
Requires-Dist: dotenv
